renewenergy/__init__.py
renewenergy/clean_data.py
renewenergy/create_scatter_plots.py
renewenergy/impute_split.py
renewenergy/plot_rmse.py
renewenergy/reading_data.py
renewenergy/split_xy_columns.py
renewenergy-0.1.2.dist-info/LICENSE
renewenergy-0.1.2.dist-info/METADATA
renewenergy-0.1.2.dist-info/WHEEL
renewenergy-0.1.2.dist-info/RECORD
