Metadata-Version: 2.1
Name: renewenergy
Version: 0.1.2
Summary: A great package to run aanalysis to help predict the renewable energy output of a country.
License: MIT
Author: Neha Menon, Caden Chan, Peter Chen, Tak Sripratak
Requires-Python: >=3.9,<4.0
Classifier: License :: OSI Approved :: MIT License
Classifier: Programming Language :: Python :: 3
Classifier: Programming Language :: Python :: 3.9
Classifier: Programming Language :: Python :: 3.10
Classifier: Programming Language :: Python :: 3.11
Classifier: Programming Language :: Python :: 3.12
Requires-Dist: matplotlib (>=3.8.4,<4.0.0)
Requires-Dist: pandas (>=2.2.1,<3.0.0)
Requires-Dist: scikit-learn (>=1.4.1.post1,<2.0.0)
